thunderlab/__init__.py
thunderlab/configfile.py
thunderlab/consoleinput.py
thunderlab/convertdata.py
thunderlab/dataloader.py
thunderlab/datawriter.py
thunderlab/eventdetection.py
thunderlab/multivariateexplorer.py
thunderlab/powerspectrum.py
thunderlab/tabledata.py
thunderlab/version.py
thunderlab/voronoi.py
thunderlab-1.7.0.dist-info/licenses/LICENSE
thunderlab-1.7.0.dist-info/METADATA
thunderlab-1.7.0.dist-info/WHEEL
thunderlab-1.7.0.dist-info/entry_points.txt
thunderlab-1.7.0.dist-info/top_level.txt
thunderlab-1.7.0.dist-info/RECORD
